python_developer_v4_cli/Python_Deployer_V4.py
python_developer_v4_cli/__init__.py
python_developer_v4_cli-4.0.2.dist-info/METADATA
python_developer_v4_cli-4.0.2.dist-info/WHEEL
python_developer_v4_cli-4.0.2.dist-info/entry_points.txt
python_developer_v4_cli-4.0.2.dist-info/top_level.txt
python_developer_v4_cli-4.0.2.dist-info/RECORD
